AUTHORS
LICENSE
MANIFEST.in
README.rst
setup.py
django_proplan.egg-info/PKG-INFO
django_proplan.egg-info/SOURCES.txt
django_proplan.egg-info/dependency_links.txt
django_proplan.egg-info/not-zip-safe
django_proplan.egg-info/top_level.txt
proplan/__init__.py
proplan/access.py
proplan/apps.py
proplan/backends.py
proplan/conf.py
proplan/decorators.py
proplan/forms.py
proplan/logic.py
proplan/models.py
proplan/routers.py
proplan/serializers.py
proplan/urls.py
proplan/version.py
proplan/locale/en/LC_MESSAGES/django.po
proplan/locale/ru/LC_MESSAGES/django.po
proplan/migrations/0001_initial.py
proplan/migrations/__init__.py
proplan/static/libs/README.txt
proplan/static/libs/csrf/csrf.js
proplan/static/libs/jquery/jquery-3.3.1.js
proplan/static/libs/jquery/jquery-3.3.1.min.js
proplan/static/libs/jquery/jquery-3.3.1.min.map
proplan/static/libs/less.js/3.9.0/less.js
proplan/static/libs/less.js/3.9.0/less.min.js
proplan/static/libs/moment.js/2.24.0/moment-with-locales.js
proplan/static/libs/moment.js/2.24.0/moment-with-locales.min.js
proplan/static/libs/twitter-bootstrap/4.3.1/css/bootstrap-grid.css
proplan/static/libs/twitter-bootstrap/4.3.1/css/bootstrap-grid.css.map
proplan/static/libs/twitter-bootstrap/4.3.1/css/bootstrap-grid.min.css
proplan/static/libs/twitter-bootstrap/4.3.1/css/bootstrap-grid.min.css.map
proplan/static/libs/twitter-bootstrap/4.3.1/css/bootstrap-reboot.css
proplan/static/libs/twitter-bootstrap/4.3.1/css/bootstrap-reboot.css.map
proplan/static/libs/twitter-bootstrap/4.3.1/css/bootstrap-reboot.min.css
proplan/static/libs/twitter-bootstrap/4.3.1/css/bootstrap-reboot.min.css.map
proplan/static/libs/twitter-bootstrap/4.3.1/css/bootstrap.css
proplan/static/libs/twitter-bootstrap/4.3.1/css/bootstrap.css.map
proplan/static/libs/twitter-bootstrap/4.3.1/css/bootstrap.min.css
proplan/static/libs/twitter-bootstrap/4.3.1/css/bootstrap.min.css.map
proplan/static/libs/twitter-bootstrap/4.3.1/js/bootstrap.bundle.js
proplan/static/libs/twitter-bootstrap/4.3.1/js/bootstrap.bundle.js.map
proplan/static/libs/twitter-bootstrap/4.3.1/js/bootstrap.bundle.min.js
proplan/static/libs/twitter-bootstrap/4.3.1/js/bootstrap.bundle.min.js.map
